dongzc1025_tobe_time_mcp/__init__.py
dongzc1025_tobe_time_mcp/server.py
dongzc1025_tobe_time_mcp-0.1.2.dist-info/METADATA
dongzc1025_tobe_time_mcp-0.1.2.dist-info/WHEEL
dongzc1025_tobe_time_mcp-0.1.2.dist-info/entry_points.txt
dongzc1025_tobe_time_mcp-0.1.2.dist-info/top_level.txt
dongzc1025_tobe_time_mcp-0.1.2.dist-info/RECORD
