Metadata-Version: 2.4
Name: dongzc1025-tobe-time-mcp
Version: 0.1.2
Summary: The MCP server to get local time
Requires-Python: >=3.12
Requires-Dist: fastmcp>=2.7.0
